functing
